httpx_http_signature/__init__.py
httpx_http_signature/version.py
httpx_http_signature-0.0.1.dist-info/LICENSE
httpx_http_signature-0.0.1.dist-info/METADATA
httpx_http_signature-0.0.1.dist-info/WHEEL
httpx_http_signature-0.0.1.dist-info/top_level.txt
httpx_http_signature-0.0.1.dist-info/RECORD
