Metadata-Version: 2.1
Name: httpx-http-signature
Version: 0.0.1
Summary: A httpx auth module for HTTP Message Signatures
Home-page: https://github.com/pyauth/httpx-http-signature
Author: Andrey Kislyuk
Author-email: kislyuk@gmail.com
License: Apache Software License
Platform: MacOS X
Platform: Posix
Classifier: Intended Audience :: Developers
Classifier: License :: OSI Approved :: Apache Software License
Classifier: Operating System :: MacOS :: MacOS X
Classifier: Operating System :: POSIX
Classifier: Programming Language :: Python
Classifier: Programming Language :: Python :: 3.7
Classifier: Programming Language :: Python :: 3.8
Classifier: Programming Language :: Python :: 3.9
Classifier: Programming Language :: Python :: 3.10
Classifier: Topic :: Software Development :: Libraries :: Python Modules
License-File: LICENSE
Requires-Dist: http-message-signatures (>=0.4.3)
Requires-Dist: http-sfv (>=0.9.3)
Requires-Dist: httpx
Provides-Extra: tests
Requires-Dist: flake8 ; extra == 'tests'
Requires-Dist: coverage ; extra == 'tests'
Requires-Dist: build ; extra == 'tests'
Requires-Dist: wheel ; extra == 'tests'
Requires-Dist: mypy ; extra == 'tests'
